colabfit/__init__.py
colabfit/cli/__init__.py
colabfit/cli/colabfit.py
colabfit/cli/utils.py
colabfit/tests/__init__.py
colabfit/tests/example.py
colabfit/tests/legacy_test_dataset.py
colabfit/tests/legacy_test_hdf5backend.py
colabfit/tests/playground.py
colabfit/tests/profilng.py
colabfit/tests/test_configurations.py
colabfit/tests/test_mongodatabase.py
colabfit/tools/__init__.py
colabfit/tools/configuration.py
colabfit/tools/configuration_set.py
colabfit/tools/database.py
colabfit/tools/dataset.py
colabfit/tools/parsers.py
colabfit/tools/property.py
colabfit/tools/property_definitions.py
colabfit/tools/schema.py
colabfit/tools/utilities.py
colabfit/tools/legacy/dataset_parser.py
colabfit/tools/legacy/hdf5_backend.py
colabfit/tools/legacy/property_settings.py
colabfit/tools/legacy/transformations.py
colabfit_kit-0.0.10.dist-info/licenses/LICENSE
docs/source/conf.py
colabfit_kit-0.0.10.dist-info/METADATA
colabfit_kit-0.0.10.dist-info/WHEEL
colabfit_kit-0.0.10.dist-info/entry_points.txt
colabfit_kit-0.0.10.dist-info/top_level.txt
colabfit_kit-0.0.10.dist-info/RECORD
