Metadata-Version: 2.4
Name: colabfit-kit
Version: 0.0.10
Summary: A suite of tools for working with training datasets for interatomic potentials
Author: ColabFit
License: The ColabFit Tools package is copyrighted by the Regents of the University of
Project-URL: Homepage, http://colabfit.org
Keywords: machine learning,interatomic potentials
Classifier: Development Status :: 3 - Alpha
Classifier: Topic :: Utilities
Classifier: License :: OSI Approved :: BSD License
Requires-Python: >=3.10
License-File: LICENSE
Requires-Dist: ase
Requires-Dist: kim_property
Requires-Dist: numpy
Requires-Dist: tqdm
Requires-Dist: markdown
Requires-Dist: plotly
Requires-Dist: django
Requires-Dist: periodictable
Requires-Dist: unidecode
Requires-Dist: notebook
Requires-Dist: vastdb
Requires-Dist: psycopg
Requires-Dist: pyspark
Requires-Dist: click>=7.0
Dynamic: license-file
